odoo/addons/partner_country_lang/README.rst
odoo/addons/partner_country_lang/__init__.py
odoo/addons/partner_country_lang/__manifest__.py
odoo/addons/partner_country_lang/i18n/es.po
odoo/addons/partner_country_lang/i18n/it.po
odoo/addons/partner_country_lang/i18n/partner_country_lang.pot
odoo/addons/partner_country_lang/models/__init__.py
odoo/addons/partner_country_lang/models/res_country.py
odoo/addons/partner_country_lang/models/res_partner.py
odoo/addons/partner_country_lang/readme/CONFIGURE.md
odoo/addons/partner_country_lang/readme/CONTRIBUTORS.md
odoo/addons/partner_country_lang/readme/DESCRIPTION.md
odoo/addons/partner_country_lang/readme/USAGE.md
odoo/addons/partner_country_lang/static/description/icon.png
odoo/addons/partner_country_lang/static/description/index.html
odoo/addons/partner_country_lang/tests/__init__.py
odoo/addons/partner_country_lang/tests/test_partner_country_lang.py
odoo/addons/partner_country_lang/views/res_country_view.xml
odoo_addon_partner_country_lang-17.0.1.0.0.4.dist-info/METADATA
odoo_addon_partner_country_lang-17.0.1.0.0.4.dist-info/WHEEL
odoo_addon_partner_country_lang-17.0.1.0.0.4.dist-info/top_level.txt
odoo_addon_partner_country_lang-17.0.1.0.0.4.dist-info/RECORD
